tkintertools/__init__.py
tkintertools/constants.py
tkintertools/exceptions.py
tkintertools/main.py
tkintertools/tools_3d.py
tkintertools-2.6.21.1.dist-info/LICENSE.txt
tkintertools-2.6.21.1.dist-info/METADATA
tkintertools-2.6.21.1.dist-info/WHEEL
tkintertools-2.6.21.1.dist-info/top_level.txt
tkintertools-2.6.21.1.dist-info/RECORD
