Metadata-Version: 2.1
Name: tkintertools
Version: 2.6.21.1
Summary: The tkintertools module is an auxiliary module of the tkinter module.
Home-page: https://github.com/Xiaokang2022/tkintertools
Author: Xiaokang2022
Author-email: 2951256653@qq.com
Maintainer: Xiaokang2022
Maintainer-email: 2951256653@qq.com
License: MulanPSL-2.0
Keywords: tkinter,tkintertools,GUI,tools
Classifier: Programming Language :: Python :: 3
Classifier: License :: OSI Approved :: Mulan Permissive Software License v2 (MulanPSL-2.0)
Classifier: Operating System :: OS Independent
Requires-Python: >=3.8
License-File: LICENSE.txt
